Workbook

Sheet Premissas
A1: PRIME STEP — Premissas do Modelo
A2: Células em azul sobre fundo amarelo são premissas editáveis. Ajuste os valores e todo o resto recalcula automaticamente.
A4: Precificação e custo variável
A5: Ticket médio por par (R$) | B5: 140
A6: Custo variável por par (R$) | B6: 20
A7: Margem de contribuição por par (R$) | B7: =B5-B6 -> 120
A8: Margem de contribuição (%) | B8: =B7/B5 -> 0.85714286
A10: Operação
A11: Dias de operação por mês | B11: 26
A12: Custo fixo mensal (R$) | B12: 300
A14: Capital e investimento inicial
A15: Capital aportado pelo sócio (R$) | B15: 15000
A16: Investimento inicial — equipamentos (R$) | B16: 5000
A17: Investimento inicial — estoque de insumos (R$) | B17: 1500
A18: Reserva para marketing e capital de giro (R$) | B18: =B15-B16-B17 -> 8500
A20: Meta de crescimento
A21: Volume atual (pares/dia) | B21: 0.5
A22: Meta de volume — dezembro/26 (pares/dia) | B22: 3
A24: Ramp mensal — volume e marketing (set–dez/2026)
B25: Set/26 | C25: Out/26 | D25: Nov/26 | E25: Dez/26
A26: Pares/dia planejado | B26: 1 | C26: 1.75 | D26: 2.4 | E26: 3
A27: Investimento em tráfego pago (R$) | B27: 1000 | C27: 1500 | D27: 1750 | E27: 1750

Sheet Volume e Receita
A1: Projeção de Volume e Receita — Set a Dez/2026
A3: Mês | B3: Pares/dia | C3: Dias de operação | D3: Volume mensal (pares) | E3: Ticket médio (R$) | F3: Receita (R$)
A4: Set/26 | B4: =Premissas!B26 -> 1 | C4: =Premissas!$B$11 -> 26 | D4: =B4*C4 -> 26 | E4: =Premissas!$B$5 -> 140 | F4: =D4*E4 -> 3640
A5: Out/26 | B5: =Premissas!C26 -> 1.75 | C5: =Premissas!$B$11 -> 26 | D5: =B5*C5 -> 45.5 | E5: =Premissas!$B$5 -> 140 | F5: =D5*E5 -> 6370
A6: Nov/26 | B6: =Premissas!D26 -> 2.4 | C6: =Premissas!$B$11 -> 26 | D6: =B6*C6 -> 62.4 | E6: =Premissas!$B$5 -> 140 | F6: =D6*E6 -> 8736
A7: Dez/26 | B7: =Premissas!E26 -> 3 | C7: =Premissas!$B$11 -> 26 | D7: =B7*C7 -> 78 | E7: =Premissas!$B$5 -> 140 | F7: =D7*E7 -> 10920
A8: Total (set–dez) | D8: =SUM(D4:D7) -> 211.9 | F8: =SUM(F4:F7) -> 29666

Sheet Fluxo de Caixa
A1: Fluxo de Caixa Projetado — Implantação a Dez/2026
A3: Mês | B3: Receita (R$) | C3: Custo variável (R$) | D3: Marketing (R$) | E3: Custo fixo (R$) | F3: Lucro líquido (R$) | G3: Saldo inicial (R$) | H3: Saldo final (R$)
A4: Implantação (pré-set) | B4: =0 -> 0 | C4: =0 -> 0 | D4: =0 -> 0 | E4: =0 -> 0 | F4: =-(Premissas!B16+Premissas!B17) -> -6500 | G4: =Premissas!B15 -> 15000 | H4: =G4+F4 -> 8500
A5: Set/26 | B5: ='Volume e Receita'!F4 -> 3640 | C5: ='Volume e Receita'!D4*Premissas!$B$6 -> 520 | D5: =Premissas!B27 -> 1000 | E5: =Premissas!$B$12 -> 300 | F5: =B5-C5-D5-E5 -> 1820 | G5: =H4 -> 8500 | H5: =G5+F5 -> 10320
A6: Out/26 | B6: ='Volume e Receita'!F5 -> 6370 | C6: ='Volume e Receita'!D5*Premissas!$B$6 -> 910 | D6: =Premissas!C27 -> 1500 | E6: =Premissas!$B$12 -> 300 | F6: =B6-C6-D6-E6 -> 3660 | G6: =H5 -> 10320 | H6: =G6+F6 -> 13980
A7: Nov/26 | B7: ='Volume e Receita'!F6 -> 8736 | C7: ='Volume e Receita'!D6*Premissas!$B$6 -> 1248 | D7: =Premissas!D27 -> 1750 | E7: =Premissas!$B$12 -> 300 | F7: =B7-C7-D7-E7 -> 5438 | G7: =H6 -> 13980 | H7: =G7+F7 -> 19418
A8: Dez/26 | B8: ='Volume e Receita'!F7 -> 10920 | C8: ='Volume e Receita'!D7*Premissas!$B$6 -> 1560 | D8: =Premissas!E27 -> 1750 | E8: =Premissas!$B$12 -> 300 | F8: =B8-C8-D8-E8 -> 7310 | G8: =H7 -> 19418 | H8: =G8+F8 -> 26728
A9: Total (set–dez) | B9: =SUM(B5:B8) -> 29666 | C9: =SUM(C5:C8) -> 4238 | D9: =SUM(D5:D8) -> 6000 | E9: =SUM(E5:E8) -> 1200 | F9: =SUM(F5:F8) -> 18228 | H9: =H8 -> 26728

Sheet Uso do Capital
A1: Uso do Capital do Sócio (R$ 15.000)
A3: Item | B3: Valor (R$) | C3: % do capital
A4: Equipamentos (máquina a vapor, escovas, secador etc.) | B4: =Premissas!B16 -> 5000 | C4: =B4/Premissas!$B$15 -> 0.33333333
A5: Estoque inicial de insumos | B5: =Premissas!B17 -> 1500 | C5: =B5/Premissas!$B$15 -> 0.1
A6: Tráfego pago (set–dez/26) | B6: =SUM(Premissas!B27:E27) -> 6000 | C6: =B6/Premissas!$B$15 -> 0.4
A7: Capital de giro / reserva | B7: =Premissas!$B$15-B4-B5-B6 -> 2500 | C7: =B7/Premissas!$B$15 -> 0.16666667
A8: Total | B8: =SUM(B4:B7) -> 15000 | C8: =SUM(C4:C7) -> 1

Sheet Ponto de Equilíbrio
A1: Ponto de Equilíbrio Mensal
A3: Mês | B3: Custos fixos + marketing (R$) | C3: Margem de contrib./par (R$) | D3: Pares/mês p/ empatar | E3: Pares/dia p/ empatar | F3: Pares/dia planejado | G3: Margem de segurança (%)
A4: Set/26 | B4: =Premissas!B27+Premissas!$B$12 -> 1300 | C4: =Premissas!$B$7 -> 120 | D4: =B4/C4 -> 10.833333 | E4: =D4/Premissas!$B$11 -> 0.41666667 | F4: =Premissas!B26 -> 1 | G4: =IFERROR((F4-E4)/F4,0) -> 0.58333333
A5: Out/26 | B5: =Premissas!C27+Premissas!$B$12 -> 1800 | C5: =Premissas!$B$7 -> 120 | D5: =B5/C5 -> 15 | E5: =D5/Premissas!$B$11 -> 0.57692308 | F5: =Premissas!C26 -> 1.75 | G5: =IFERROR((F5-E5)/F5,0) -> 0.67032967
A6: Nov/26 | B6: =Premissas!D27+Premissas!$B$12 -> 2050 | C6: =Premissas!$B$7 -> 120 | D6: =B6/C6 -> 17.083333 | E6: =D6/Premissas!$B$11 -> 0.65705128 | F6: =Premissas!D26 -> 2.4 | G6: =IFERROR((F6-E6)/F6,0) -> 0.72622863
A7: Dez/26 | B7: =Premissas!E27+Premissas!$B$12 -> 2050 | C7: =Premissas!$B$7 -> 120 | D7: =B7/C7 -> 17.083333 | E7: =D7/Premissas!$B$11 -> 0.65705128 | F7: =Premissas!E26 -> 3 | G7: =IFERROR((F7-E7)/F7,0) -> 0.78098291

Sheet Resumo
A1: Resumo Executivo — Prime Step
A2: Plano de crescimento — set a dez/2026
A4: Ticket médio (R$) | B4: =Premissas!B5 -> 140
A5: Margem de contribuição (%) | B5: =Premissas!B8 -> 0.85714286
A6: Volume atual (pares/dia) | B6: =Premissas!B21 -> 0.5
A7: Meta de volume — dez/26 (pares/dia) | B7: =Premissas!B22 -> 3
A8: Crescimento de volume (x) | B8: =Premissas!B22/Premissas!B21 -> 6
A9: Receita total projetada (set–dez) | B9: ='Volume e Receita'!F8 -> 29666
A10: Lucro líquido total (set–dez) | B10: ='Fluxo de Caixa'!F9 -> 18228
A11: Saldo de caixa em 31/dez/26 | B11: ='Fluxo de Caixa'!H8 -> 26728
